License.txt .txt
README.md
setup.py
PVMB.egg-info/PKG-INFO
PVMB.egg-info/SOURCES.txt
PVMB.egg-info/dependency_links.txt
PVMB.egg-info/top_level.txt
src/__init__.py
src/box.py