Metadata-Version: 2.1
Name: PVMB
Version: 0.0.1
Summary: MessageBox package
Author: Batte
License-File: License.txt .txt
